festivalcobra/__init__.py
festivalcobra-0.0.0.dist-info/LICENSE
festivalcobra-0.0.0.dist-info/METADATA
festivalcobra-0.0.0.dist-info/WHEEL
festivalcobra-0.0.0.dist-info/RECORD
